jsonclasses_server/__init__.py
jsonclasses_server/aconf.py
jsonclasses_server/actx.py
jsonclasses_server/api.py
jsonclasses_server/api_class.py
jsonclasses_server/api_object.py
jsonclasses_server/api_record.py
jsonclasses_server/auth_conf.py
jsonclasses_server/authorized.py
jsonclasses_server/create_fastapi_server.py
jsonclasses_server/create_flask_server.py
jsonclasses_server/create_server.py
jsonclasses_server/decode_jwt_token.py
jsonclasses_server/encode_jwt_token.py
jsonclasses_server/excs.py
jsonclasses_server/jwt_token.py
jsonclasses_server/nameutils.py
jsonclasses_server/py.typed
jsonclasses_server/server.py
tests/__init__.py
tests/test_fastapi_server.py
tests/test_flask_server.py
tests/test_server.py
tests/test_simple_request.py
jsonclasses_server-3.3.0.dist-info/LICENSE
jsonclasses_server-3.3.0.dist-info/METADATA
jsonclasses_server-3.3.0.dist-info/WHEEL
jsonclasses_server-3.3.0.dist-info/top_level.txt
jsonclasses_server-3.3.0.dist-info/RECORD
