Metadata-Version: 2.1
Name: jsonclasses-server
Version: 3.3.0
Summary: jsonclasses server
Home-page: https://github.com/fillmula/jsonclasses-server
Author: Fillmula Inc.
Author-email: victor.teo@fillmula.com
License: MIT
Platform: UNKNOWN
Requires-Python: >=3.10
License-File: LICENSE
Requires-Dist: jsonclasses (<4.0.0,>=3.3.0)
Requires-Dist: jsonclasses-pymongo (<4.0.0,>=3.3.0)
Requires-Dist: qsparser (<2.0.0,>=1.0.1)
Requires-Dist: thunderlight (<0.6.0,>=0.5.0)
Requires-Dist: pyjwt (<3.0.0,>=2.3.0)
